fido2client/__init__.py
fido2client/client.py
fido2client-0.10.2.dist-info/LICENSE
fido2client-0.10.2.dist-info/METADATA
fido2client-0.10.2.dist-info/WHEEL
fido2client-0.10.2.dist-info/top_level.txt
fido2client-0.10.2.dist-info/RECORD
