Metadata-Version: 2.1
Name: fido2client
Version: 0.10.2
Summary: WebAuthn API FIDO2 client
Home-page: https://github.com/origliante/python-fido2-client
Author: origliante
Author-email: please.visit.github@page.nowhere
License: UNKNOWN
Platform: UNKNOWN
Classifier: Programming Language :: Python :: 3
Classifier: License :: OSI Approved :: MIT License
Classifier: Operating System :: OS Independent
Classifier: Topic :: Internet
Classifier: Topic :: Security :: Cryptography
Classifier: Topic :: Software Development :: Libraries :: Python Modules
Requires-Python: >=3.5
Requires-Dist: fido2
Requires-Dist: cbor2
Requires-Dist: requests
Requires-Dist: simplejson
